<?xml version="1.0" encoding="utf-8"?>
<xliff xmlns="urn:oasis:names:tc:xliff:document:1.2" xmlns:xsi="http://www.w3.org/2001/XMLSchema-instance" version="1.2" xsi:schemaLocation="urn:oasis:names:tc:xliff:document:1.2 xliff-core-1.2-transitional.xsd">
  <file datatype="xml" original="DataGridItemAutomationPeer.xml" source-language="en-US" target-language="pt-BR">
    <header>
      <tool tool-id="mdxliff" tool-name="mdxliff" tool-version="1.0-15c36f0" tool-company="Microsoft" />
      <xliffext:skl_file_name xmlns:xliffext="urn:microsoft:content:schema:xliffextensions">02cd5861-7ce2-4a82-b358-31f8435a0ac592a4efeb595e127da5db7f3798d107d23e589f56.skl</xliffext:skl_file_name>
      <xliffext:version xmlns:xliffext="urn:microsoft:content:schema:xliffextensions">1.2</xliffext:version>
      <xliffext:ms.openlocfilehash xmlns:xliffext="urn:microsoft:content:schema:xliffextensions">92a4efeb595e127da5db7f3798d107d23e589f56</xliffext:ms.openlocfilehash>
      <xliffext:ms.sourcegitcommit xmlns:xliffext="urn:microsoft:content:schema:xliffextensions">d31dc2ede16f6f7bc64e90d9f897ff54c4e3869b</xliffext:ms.sourcegitcommit>
      <xliffext:ms.lasthandoff xmlns:xliffext="urn:microsoft:content:schema:xliffextensions">04/03/2018</xliffext:ms.lasthandoff>
      <xliffext:moniker_ids xmlns:xliffext="urn:microsoft:content:schema:xliffextensions">netframework-4.5.1,netframework-4.5.2,netframework-4.5,netframework-4.6.1,netframework-4.6.2,netframework-4.6,netframework-4.7.1,netframework-4.7</xliffext:moniker_ids>
    </header>
    <body>
      <group id="content" extype="content">
        <trans-unit id="101" translate="yes" xml:space="preserve" uid="T:System.Windows.Automation.Peers.DataGridItemAutomationPeer">
          <source>Exposes <ph id="ph1">&lt;see cref="T:System.Windows.Controls.DataGridRow" /&gt;</ph> types to UI Automation.</source>
          <target state="translated">Expõe tipos <ph id="ph1">&lt;see cref="T:System.Windows.Controls.DataGridRow" /&gt;</ph> à Automação de Interface do Usuário.</target>       </trans-unit>
        <trans-unit id="102" translate="yes" xml:space="preserve" uid="T:System.Windows.Automation.Peers.DataGridItemAutomationPeer">
          <source>The <ph id="ph1">&lt;see cref="T:System.Windows.Controls.DataGridRow" /&gt;</ph> may or may not actually exist in memory.</source>
          <target state="translated">A <ph id="ph1">&lt;see cref="T:System.Windows.Controls.DataGridRow" /&gt;</ph> pode ou não existir, de fato, na memória.</target>       </trans-unit>
        <trans-unit id="103" translate="yes" xml:space="preserve" uid="M:System.Windows.Automation.Peers.DataGridItemAutomationPeer.#ctor(System.Object,System.Windows.Automation.Peers.DataGridAutomationPeer)">
          <source>The data item in the <ph id="ph1">&lt;see cref="P:System.Windows.Controls.ItemsControl.Items" /&gt;</ph> collection that is associated with this <ph id="ph2">&lt;see cref="T:System.Windows.Automation.Peers.DataGridItemAutomationPeer" /&gt;</ph>.</source>
          <target state="translated">O item de dados na coleção <ph id="ph1">&lt;see cref="P:System.Windows.Controls.ItemsControl.Items" /&gt;</ph> que está associado a este <ph id="ph2">&lt;see cref="T:System.Windows.Automation.Peers.DataGridItemAutomationPeer" /&gt;</ph>.</target>       </trans-unit>
        <trans-unit id="104" translate="yes" xml:space="preserve" uid="M:System.Windows.Automation.Peers.DataGridItemAutomationPeer.#ctor(System.Object,System.Windows.Automation.Peers.DataGridAutomationPeer)">
          <source>The <ph id="ph1">&lt;see cref="T:System.Windows.Automation.Peers.DataGridAutomationPeer" /&gt;</ph> that is associated with the <ph id="ph2">&lt;see cref="T:System.Windows.Controls.DataGrid" /&gt;</ph> that holds the <ph id="ph3">&lt;see cref="P:System.Windows.Controls.ItemsControl.Items" /&gt;</ph> collection.</source>
          <target state="translated">O <ph id="ph1">&lt;see cref="T:System.Windows.Automation.Peers.DataGridAutomationPeer" /&gt;</ph> associado ao <ph id="ph2">&lt;see cref="T:System.Windows.Controls.DataGrid" /&gt;</ph> que contém a coleção <ph id="ph3">&lt;see cref="P:System.Windows.Controls.ItemsControl.Items" /&gt;</ph>.</target>       </trans-unit>
        <trans-unit id="105" translate="yes" xml:space="preserve" uid="M:System.Windows.Automation.Peers.DataGridItemAutomationPeer.#ctor(System.Object,System.Windows.Automation.Peers.DataGridAutomationPeer)">
          <source>Initializes a new instance of the <ph id="ph1">&lt;see cref="T:System.Windows.Automation.Peers.DataGridItemAutomationPeer" /&gt;</ph> class.</source>
          <target state="translated">Inicializa uma nova instância da classe <ph id="ph1">&lt;see cref="T:System.Windows.Automation.Peers.DataGridItemAutomationPeer" /&gt;</ph>.</target>       </trans-unit>
        <trans-unit id="106" translate="yes" xml:space="preserve" uid="M:System.Windows.Automation.Peers.DataGridItemAutomationPeer.GetPattern(System.Windows.Automation.Peers.PatternInterface)">
          <source>An enumeration value that specifies the control pattern.</source>
          <target state="translated">Um valor de enumeração que especifica o padrão de controle.</target>       </trans-unit>
        <trans-unit id="107" translate="yes" xml:space="preserve" uid="M:System.Windows.Automation.Peers.DataGridItemAutomationPeer.GetPattern(System.Windows.Automation.Peers.PatternInterface)">
          <source>Returns the object that supports the specified control pattern of the element that is associated with this automation peer.</source>
          <target state="translated">Retorna o objeto que dá suporte ao padrão de controle especificado do elemento que está associado a este par de automação.</target>       </trans-unit>
        <trans-unit id="108" translate="yes" xml:space="preserve" uid="M:System.Windows.Automation.Peers.DataGridItemAutomationPeer.GetPattern(System.Windows.Automation.Peers.PatternInterface)">
          <source>The current <ph id="ph1">&lt;see cref="T:System.Windows.Automation.Peers.DataGridCellItemAutomationPeer" /&gt;</ph> object, if <ph id="ph2">&lt;paramref name="patternInterface" /&gt;</ph> is a supported value; otherwise, <ph id="ph3">&lt;see langword="null" /&gt;</ph>.</source>
          <target state="translated">O objeto <ph id="ph1">&lt;see cref="T:System.Windows.Automation.Peers.DataGridCellItemAutomationPeer" /&gt;</ph> atual, se <ph id="ph2">&lt;paramref name="patternInterface" /&gt;</ph> for um valor com suporte; caso contrário, <ph id="ph3">&lt;see langword="null" /&gt;</ph>.</target>       </trans-unit>
        <trans-unit id="109" translate="yes" xml:space="preserve" extradata="MT" uid="M:System.Windows.Automation.Peers.DataGridItemAutomationPeer.GetPattern(System.Windows.Automation.Peers.PatternInterface)">
          <source>If one of the following cases occurs, this method returns the current <ph id="ph1">&lt;xref:System.Windows.Automation.Peers.DataGridCellItemAutomationPeer&gt;</ph> object.</source>
          <target state="translated">Se uma das seguintes situações ocorrer, esse método retorna atual <ph id="ph1">&lt;xref:System.Windows.Automation.Peers.DataGridCellItemAutomationPeer&gt;</ph> objeto.</target>       </trans-unit>
        <trans-unit id="110" translate="yes" xml:space="preserve" extradata="MT" uid="M:System.Windows.Automation.Peers.DataGridItemAutomationPeer.GetPattern(System.Windows.Automation.Peers.PatternInterface)">
          <source><ph id="ph1">`patternInterface`</ph> is <ph id="ph2">&lt;xref:System.Windows.Automation.Peers.PatternInterface.Invoke?displayProperty=nameWithType&gt;</ph> and the <ph id="ph3">&lt;xref:System.Windows.Controls.DataGrid&gt;</ph> that is associated with this <ph id="ph4">&lt;xref:System.Windows.Automation.Peers.DataGridItemAutomationPeer&gt;</ph> is read-only.</source>
          <target state="translated"><ph id="ph1">`patternInterface`</ph> é <ph id="ph2">&lt;xref:System.Windows.Automation.Peers.PatternInterface.Invoke?displayProperty=nameWithType&gt;</ph> e <ph id="ph3">&lt;xref:System.Windows.Controls.DataGrid&gt;</ph> que é associada a essa <ph id="ph4">&lt;xref:System.Windows.Automation.Peers.DataGridItemAutomationPeer&gt;</ph> é somente leitura.</target>       </trans-unit>
        <trans-unit id="111" translate="yes" xml:space="preserve" extradata="MT" uid="M:System.Windows.Automation.Peers.DataGridItemAutomationPeer.GetPattern(System.Windows.Automation.Peers.PatternInterface)">
          <source><ph id="ph1">`patternInterface`</ph> is <ph id="ph2">&lt;xref:System.Windows.Automation.Peers.PatternInterface.SelectionItem?displayProperty=nameWithType&gt;</ph> and the <ph id="ph3">&lt;xref:System.Windows.Controls.DataGridRow&gt;</ph> that is associated with this <ph id="ph4">&lt;xref:System.Windows.Automation.Peers.DataGridCellAutomationPeer&gt;</ph> can be selected.</source>
          <target state="translated"><ph id="ph1">`patternInterface`</ph> é <ph id="ph2">&lt;xref:System.Windows.Automation.Peers.PatternInterface.SelectionItem?displayProperty=nameWithType&gt;</ph> e <ph id="ph3">&lt;xref:System.Windows.Controls.DataGridRow&gt;</ph> que é associada a essa <ph id="ph4">&lt;xref:System.Windows.Automation.Peers.DataGridCellAutomationPeer&gt;</ph> pode ser selecionado.</target>       </trans-unit>
        <trans-unit id="112" translate="yes" xml:space="preserve" extradata="MT" uid="M:System.Windows.Automation.Peers.DataGridItemAutomationPeer.GetPattern(System.Windows.Automation.Peers.PatternInterface)">
          <source><ph id="ph1">`patternInterface`</ph> is <ph id="ph2">&lt;xref:System.Windows.Automation.Peers.PatternInterface.ScrollItem?displayProperty=nameWithType&gt;</ph>.</source>
          <target state="translated"><ph id="ph1">`patternInterface`</ph> é <ph id="ph2">&lt;xref:System.Windows.Automation.Peers.PatternInterface.ScrollItem?displayProperty=nameWithType&gt;</ph>.</target>       </trans-unit>
        <trans-unit id="113" translate="yes" xml:space="preserve" extradata="MT" uid="M:System.Windows.Automation.Peers.DataGridItemAutomationPeer.GetPattern(System.Windows.Automation.Peers.PatternInterface)">
          <source><ph id="ph1">`patternInterface`</ph> is <ph id="ph2">&lt;xref:System.Windows.Automation.Peers.PatternInterface.Selection?displayProperty=nameWithType&gt;</ph>.</source>
          <target state="translated"><ph id="ph1">`patternInterface`</ph> é <ph id="ph2">&lt;xref:System.Windows.Automation.Peers.PatternInterface.Selection?displayProperty=nameWithType&gt;</ph>.</target>       </trans-unit>
        <trans-unit id="114" translate="yes" xml:space="preserve" uid="M:System.Windows.Automation.Peers.DataGridItemAutomationPeer.System#Windows#Automation#Provider#IInvokeProvider#Invoke">
          <source>Sends a request to activate a control and initiate its single, unambiguous action.</source>
          <target state="translated">Envia uma solicitação para ativar um controle e iniciar sua ação única não ambígua.</target>       </trans-unit>
        <trans-unit id="115" translate="yes" xml:space="preserve" extradata="MT" uid="M:System.Windows.Automation.Peers.DataGridItemAutomationPeer.System#Windows#Automation#Provider#IInvokeProvider#Invoke">
          <source>This member is an explicit interface member implementation.</source>
          <target state="translated">Este membro é uma implementação do membro de interface explícita.</target>       </trans-unit>
        <trans-unit id="116" translate="yes" xml:space="preserve" extradata="MT" uid="M:System.Windows.Automation.Peers.DataGridItemAutomationPeer.System#Windows#Automation#Provider#IInvokeProvider#Invoke">
          <source>It can be used only when the <ph id="ph1">&lt;xref:System.Windows.Automation.Peers.DataGridItemAutomationPeer&gt;</ph> instance is cast to an <ph id="ph2">&lt;xref:System.Windows.Automation.Provider.IInvokeProvider&gt;</ph> interface.</source>
          <target state="translated">Ele só pode ser usado quando a instância de <ph id="ph1">&lt;xref:System.Windows.Automation.Peers.DataGridItemAutomationPeer&gt;</ph> é convertida em uma interface de <ph id="ph2">&lt;xref:System.Windows.Automation.Provider.IInvokeProvider&gt;</ph>.</target>       </trans-unit>
        <trans-unit id="117" translate="yes" xml:space="preserve" uid="M:System.Windows.Automation.Peers.DataGridItemAutomationPeer.System#Windows#Automation#Provider#IItemContainerProvider#FindItemByProperty(System.Windows.Automation.Provider.IRawElementProviderSimple,System.Int32,System.Object)">
          <source>The item in the container after which to begin the search.</source>
          <target state="translated">O item no contêiner após o qual iniciar a pesquisa.</target>       </trans-unit>
        <trans-unit id="118" translate="yes" xml:space="preserve" uid="M:System.Windows.Automation.Peers.DataGridItemAutomationPeer.System#Windows#Automation#Provider#IItemContainerProvider#FindItemByProperty(System.Windows.Automation.Provider.IRawElementProviderSimple,System.Int32,System.Object)">
          <source>The property that contains the value to retrieve.</source>
          <target state="translated">A propriedade que contém o valor a ser recuperado.</target>       </trans-unit>
        <trans-unit id="119" translate="yes" xml:space="preserve" uid="M:System.Windows.Automation.Peers.DataGridItemAutomationPeer.System#Windows#Automation#Provider#IItemContainerProvider#FindItemByProperty(System.Windows.Automation.Provider.IRawElementProviderSimple,System.Int32,System.Object)">
          <source>The value to retrieve.</source>
          <target state="translated">O valor a ser recuperado.</target>       </trans-unit>
        <trans-unit id="120" translate="yes" xml:space="preserve" uid="M:System.Windows.Automation.Peers.DataGridItemAutomationPeer.System#Windows#Automation#Provider#IItemContainerProvider#FindItemByProperty(System.Windows.Automation.Provider.IRawElementProviderSimple,System.Int32,System.Object)">
          <source>Retrieves an element by the specified property value.</source>
          <target state="translated">Recupera um elemento pelo valor da propriedade especificado.</target>       </trans-unit>
        <trans-unit id="121" translate="yes" xml:space="preserve" uid="M:System.Windows.Automation.Peers.DataGridItemAutomationPeer.System#Windows#Automation#Provider#IItemContainerProvider#FindItemByProperty(System.Windows.Automation.Provider.IRawElementProviderSimple,System.Int32,System.Object)">
          <source>The first item that matches the search criterion; otherwise, <ph id="ph1">&lt;see langword="null" /&gt;</ph> if no items match.</source>
          <target state="translated">O primeiro item que corresponde ao critério de pesquisa; caso contrário, <ph id="ph1">&lt;see langword="null" /&gt;</ph> se nenhum item corresponder a ele.</target>       </trans-unit>
        <trans-unit id="122" translate="yes" xml:space="preserve" extradata="MT" uid="M:System.Windows.Automation.Peers.DataGridItemAutomationPeer.System#Windows#Automation#Provider#IItemContainerProvider#FindItemByProperty(System.Windows.Automation.Provider.IRawElementProviderSimple,System.Int32,System.Object)">
          <source>This member is an explicit interface member implementation.</source>
          <target state="translated">Este membro é uma implementação do membro de interface explícita.</target>       </trans-unit>
        <trans-unit id="123" translate="yes" xml:space="preserve" extradata="MT" uid="M:System.Windows.Automation.Peers.DataGridItemAutomationPeer.System#Windows#Automation#Provider#IItemContainerProvider#FindItemByProperty(System.Windows.Automation.Provider.IRawElementProviderSimple,System.Int32,System.Object)">
          <source>It can be used only when the <ph id="ph1">&lt;xref:System.Windows.Automation.Peers.DataGridItemAutomationPeer&gt;</ph> instance is cast to an <ph id="ph2">&lt;xref:System.Windows.Automation.Provider.IItemContainerProvider&gt;</ph> interface.</source>
          <target state="translated">Ele só pode ser usado quando a instância de <ph id="ph1">&lt;xref:System.Windows.Automation.Peers.DataGridItemAutomationPeer&gt;</ph> é convertida em uma interface de <ph id="ph2">&lt;xref:System.Windows.Automation.Provider.IItemContainerProvider&gt;</ph>.</target>       </trans-unit>
        <trans-unit id="124" translate="yes" xml:space="preserve" uid="M:System.Windows.Automation.Peers.DataGridItemAutomationPeer.System#Windows#Automation#Provider#IScrollItemProvider#ScrollIntoView">
          <source>Scrolls the content area of a container object to display the control within the visible region (viewport) of the container.</source>
          <target state="translated">Rola a área de conteúdo de um objeto contêiner para exibir o controle dentro da região visível (visor) do contêiner.</target>       </trans-unit>
        <trans-unit id="125" translate="yes" xml:space="preserve" extradata="MT" uid="M:System.Windows.Automation.Peers.DataGridItemAutomationPeer.System#Windows#Automation#Provider#IScrollItemProvider#ScrollIntoView">
          <source>This member is an explicit interface member implementation.</source>
          <target state="translated">Este membro é uma implementação do membro de interface explícita.</target>       </trans-unit>
        <trans-unit id="126" translate="yes" xml:space="preserve" extradata="MT" uid="M:System.Windows.Automation.Peers.DataGridItemAutomationPeer.System#Windows#Automation#Provider#IScrollItemProvider#ScrollIntoView">
          <source>It can be used only when the <ph id="ph1">&lt;xref:System.Windows.Automation.Peers.DataGridItemAutomationPeer&gt;</ph> instance is cast to an <ph id="ph2">&lt;xref:System.Windows.Automation.Provider.IScrollItemProvider&gt;</ph> interface.</source>
          <target state="translated">Ele só pode ser usado quando a instância de <ph id="ph1">&lt;xref:System.Windows.Automation.Peers.DataGridItemAutomationPeer&gt;</ph> é convertida em uma interface de <ph id="ph2">&lt;xref:System.Windows.Automation.Provider.IScrollItemProvider&gt;</ph>.</target>       </trans-unit>
        <trans-unit id="127" translate="yes" xml:space="preserve" uid="M:System.Windows.Automation.Peers.DataGridItemAutomationPeer.System#Windows#Automation#Provider#ISelectionItemProvider#AddToSelection">
          <source>Adds the current element to the collection of selected items.</source>
          <target state="translated">Adiciona o elemento atual à coleção de itens selecionados.</target>       </trans-unit>
        <trans-unit id="128" translate="yes" xml:space="preserve" extradata="MT" uid="M:System.Windows.Automation.Peers.DataGridItemAutomationPeer.System#Windows#Automation#Provider#ISelectionItemProvider#AddToSelection">
          <source>This member is an explicit interface member implementation.</source>
          <target state="translated">Este membro é uma implementação do membro de interface explícita.</target>       </trans-unit>
        <trans-unit id="129" translate="yes" xml:space="preserve" extradata="MT" uid="M:System.Windows.Automation.Peers.DataGridItemAutomationPeer.System#Windows#Automation#Provider#ISelectionItemProvider#AddToSelection">
          <source>It can be used only when the <ph id="ph1">&lt;xref:System.Windows.Automation.Peers.DataGridItemAutomationPeer&gt;</ph> instance is cast to an <ph id="ph2">&lt;xref:System.Windows.Automation.Provider.ISelectionItemProvider&gt;</ph> interface.</source>
          <target state="translated">Ele só pode ser usado quando a instância de <ph id="ph1">&lt;xref:System.Windows.Automation.Peers.DataGridItemAutomationPeer&gt;</ph> é convertida em uma interface de <ph id="ph2">&lt;xref:System.Windows.Automation.Provider.ISelectionItemProvider&gt;</ph>.</target>       </trans-unit>
        <trans-unit id="130" translate="yes" xml:space="preserve" uid="P:System.Windows.Automation.Peers.DataGridItemAutomationPeer.System#Windows#Automation#Provider#ISelectionItemProvider#IsSelected">
          <source>Gets a value that indicates whether an item is selected.</source>
          <target state="translated">Obtém um valor que indica se um item está selecionado.</target>       </trans-unit>
        <trans-unit id="131" translate="yes" xml:space="preserve" extradata="MT" uid="P:System.Windows.Automation.Peers.DataGridItemAutomationPeer.System#Windows#Automation#Provider#ISelectionItemProvider#IsSelected">
          <source><ph id="ph1">&lt;see langword="true" /&gt;</ph> if the element is selected; otherwise, <ph id="ph2">&lt;see langword="false" /&gt;</ph>.</source>
          <target state="translated"><ph id="ph1">&lt;see langword="true" /&gt;</ph> Se o elemento for selecionado; Caso contrário, <ph id="ph2">&lt;see langword="false" /&gt;</ph>.</target>       </trans-unit>
        <trans-unit id="132" translate="yes" xml:space="preserve" extradata="MT" uid="P:System.Windows.Automation.Peers.DataGridItemAutomationPeer.System#Windows#Automation#Provider#ISelectionItemProvider#IsSelected">
          <source>This member is an explicit interface member implementation.</source>
          <target state="translated">Este membro é uma implementação do membro de interface explícita.</target>       </trans-unit>
        <trans-unit id="133" translate="yes" xml:space="preserve" extradata="MT" uid="P:System.Windows.Automation.Peers.DataGridItemAutomationPeer.System#Windows#Automation#Provider#ISelectionItemProvider#IsSelected">
          <source>It can be used only when the <ph id="ph1">&lt;xref:System.Windows.Automation.Peers.DataGridItemAutomationPeer&gt;</ph> instance is cast to an <ph id="ph2">&lt;xref:System.Windows.Automation.Provider.ISelectionItemProvider&gt;</ph> interface.</source>
          <target state="translated">Ele só pode ser usado quando a instância de <ph id="ph1">&lt;xref:System.Windows.Automation.Peers.DataGridItemAutomationPeer&gt;</ph> é convertida em uma interface de <ph id="ph2">&lt;xref:System.Windows.Automation.Provider.ISelectionItemProvider&gt;</ph>.</target>       </trans-unit>
        <trans-unit id="134" translate="yes" xml:space="preserve" uid="M:System.Windows.Automation.Peers.DataGridItemAutomationPeer.System#Windows#Automation#Provider#ISelectionItemProvider#RemoveFromSelection">
          <source>Removes the current element from the collection of selected items.</source>
          <target state="translated">Remove o elemento atual da coleção de itens selecionados.</target>       </trans-unit>
        <trans-unit id="135" translate="yes" xml:space="preserve" extradata="MT" uid="M:System.Windows.Automation.Peers.DataGridItemAutomationPeer.System#Windows#Automation#Provider#ISelectionItemProvider#RemoveFromSelection">
          <source>This member is an explicit interface member implementation.</source>
          <target state="translated">Este membro é uma implementação do membro de interface explícita.</target>       </trans-unit>
        <trans-unit id="136" translate="yes" xml:space="preserve" extradata="MT" uid="M:System.Windows.Automation.Peers.DataGridItemAutomationPeer.System#Windows#Automation#Provider#ISelectionItemProvider#RemoveFromSelection">
          <source>It can be used only when the <ph id="ph1">&lt;xref:System.Windows.Automation.Peers.DataGridItemAutomationPeer&gt;</ph> instance is cast to an <ph id="ph2">&lt;xref:System.Windows.Automation.Provider.ISelectionItemProvider&gt;</ph> interface.</source>
          <target state="translated">Ele só pode ser usado quando a instância de <ph id="ph1">&lt;xref:System.Windows.Automation.Peers.DataGridItemAutomationPeer&gt;</ph> é convertida em uma interface de <ph id="ph2">&lt;xref:System.Windows.Automation.Provider.ISelectionItemProvider&gt;</ph>.</target>       </trans-unit>
        <trans-unit id="137" translate="yes" xml:space="preserve" uid="M:System.Windows.Automation.Peers.DataGridItemAutomationPeer.System#Windows#Automation#Provider#ISelectionItemProvider#Select">
          <source>Clears any selected items and then selects the current element.</source>
          <target state="translated">Desmarca os itens selecionados e, em seguida, seleciona o elemento atual.</target>       </trans-unit>
        <trans-unit id="138" translate="yes" xml:space="preserve" extradata="MT" uid="M:System.Windows.Automation.Peers.DataGridItemAutomationPeer.System#Windows#Automation#Provider#ISelectionItemProvider#Select">
          <source>This member is an explicit interface member implementation.</source>
          <target state="translated">Este membro é uma implementação do membro de interface explícita.</target>       </trans-unit>
        <trans-unit id="139" translate="yes" xml:space="preserve" extradata="MT" uid="M:System.Windows.Automation.Peers.DataGridItemAutomationPeer.System#Windows#Automation#Provider#ISelectionItemProvider#Select">
          <source>It can be used only when the <ph id="ph1">&lt;xref:System.Windows.Automation.Peers.DataGridItemAutomationPeer&gt;</ph> instance is cast to an <ph id="ph2">&lt;xref:System.Windows.Automation.Provider.ISelectionItemProvider&gt;</ph> interface.</source>
          <target state="translated">Ele só pode ser usado quando a instância de <ph id="ph1">&lt;xref:System.Windows.Automation.Peers.DataGridItemAutomationPeer&gt;</ph> é convertida em uma interface de <ph id="ph2">&lt;xref:System.Windows.Automation.Provider.ISelectionItemProvider&gt;</ph>.</target>       </trans-unit>
        <trans-unit id="140" translate="yes" xml:space="preserve" uid="P:System.Windows.Automation.Peers.DataGridItemAutomationPeer.System#Windows#Automation#Provider#ISelectionItemProvider#SelectionContainer">
          <source>Gets the UI Automation provider that implements <ph id="ph1">&lt;see cref="T:System.Windows.Automation.Provider.ISelectionProvider" /&gt;</ph> and acts as the container for the calling object.</source>
          <target state="translated">Obtém o provedor de Automação da Interface do Usuário que implementa <ph id="ph1">&lt;see cref="T:System.Windows.Automation.Provider.ISelectionProvider" /&gt;</ph> e atua como o contêiner do objeto de chamada.</target>       </trans-unit>
        <trans-unit id="141" translate="yes" xml:space="preserve" extradata="MT" uid="P:System.Windows.Automation.Peers.DataGridItemAutomationPeer.System#Windows#Automation#Provider#ISelectionItemProvider#SelectionContainer">
          <source>The provider for the <ph id="ph1">&lt;see cref="T:System.Windows.Controls.DataGrid" /&gt;</ph> control.</source>
          <target state="translated">O provedor para o <ph id="ph1">&lt;see cref="T:System.Windows.Controls.DataGrid" /&gt;</ph> controle.</target>       </trans-unit>
        <trans-unit id="142" translate="yes" xml:space="preserve" extradata="MT" uid="P:System.Windows.Automation.Peers.DataGridItemAutomationPeer.System#Windows#Automation#Provider#ISelectionItemProvider#SelectionContainer">
          <source>This member is an explicit interface member implementation.</source>
          <target state="translated">Este membro é uma implementação do membro de interface explícita.</target>       </trans-unit>
        <trans-unit id="143" translate="yes" xml:space="preserve" extradata="MT" uid="P:System.Windows.Automation.Peers.DataGridItemAutomationPeer.System#Windows#Automation#Provider#ISelectionItemProvider#SelectionContainer">
          <source>It can be used only when the <ph id="ph1">&lt;xref:System.Windows.Automation.Peers.DataGridItemAutomationPeer&gt;</ph> instance is cast to an <ph id="ph2">&lt;xref:System.Windows.Automation.Provider.ISelectionItemProvider&gt;</ph> interface.</source>
          <target state="translated">Ele só pode ser usado quando a instância de <ph id="ph1">&lt;xref:System.Windows.Automation.Peers.DataGridItemAutomationPeer&gt;</ph> é convertida em uma interface de <ph id="ph2">&lt;xref:System.Windows.Automation.Provider.ISelectionItemProvider&gt;</ph>.</target>       </trans-unit>
        <trans-unit id="144" translate="yes" xml:space="preserve" uid="P:System.Windows.Automation.Peers.DataGridItemAutomationPeer.System#Windows#Automation#Provider#ISelectionProvider#CanSelectMultiple">
          <source>Gets a value that indicates whether the UI Automation provider allows more than one child element to be selected concurrently.</source>
          <target state="translated">Obtém um valor que indica se o provedor de Automação da Interface do Usuário permite que mais de um elemento filho seja selecionado simultaneamente.</target>       </trans-unit>
        <trans-unit id="145" translate="yes" xml:space="preserve" extradata="MT" uid="P:System.Windows.Automation.Peers.DataGridItemAutomationPeer.System#Windows#Automation#Provider#ISelectionProvider#CanSelectMultiple">
          <source><ph id="ph1">&lt;see langword="true" /&gt;</ph> if multiple selection is allowed; otherwise, <ph id="ph2">&lt;see langword="false" /&gt;</ph>.</source>
          <target state="translated"><ph id="ph1">&lt;see langword="true" /&gt;</ph> Se a seleção múltipla é permitida. Caso contrário, <ph id="ph2">&lt;see langword="false" /&gt;</ph>.</target>       </trans-unit>
        <trans-unit id="146" translate="yes" xml:space="preserve" extradata="MT" uid="P:System.Windows.Automation.Peers.DataGridItemAutomationPeer.System#Windows#Automation#Provider#ISelectionProvider#CanSelectMultiple">
          <source>This member is an explicit interface member implementation.</source>
          <target state="translated">Este membro é uma implementação do membro de interface explícita.</target>       </trans-unit>
        <trans-unit id="147" translate="yes" xml:space="preserve" extradata="MT" uid="P:System.Windows.Automation.Peers.DataGridItemAutomationPeer.System#Windows#Automation#Provider#ISelectionProvider#CanSelectMultiple">
          <source>It can be used only when the <ph id="ph1">&lt;xref:System.Windows.Automation.Peers.DataGridItemAutomationPeer&gt;</ph> instance is cast to an <ph id="ph2">&lt;xref:System.Windows.Automation.Provider.ISelectionProvider&gt;</ph> interface.</source>
          <target state="translated">Ele só pode ser usado quando a instância de <ph id="ph1">&lt;xref:System.Windows.Automation.Peers.DataGridItemAutomationPeer&gt;</ph> é convertida em uma interface de <ph id="ph2">&lt;xref:System.Windows.Automation.Provider.ISelectionProvider&gt;</ph>.</target>       </trans-unit>
        <trans-unit id="148" translate="yes" xml:space="preserve" uid="M:System.Windows.Automation.Peers.DataGridItemAutomationPeer.System#Windows#Automation#Provider#ISelectionProvider#GetSelection">
          <source>Retrieves a UI Automation provider for each child element that is selected.</source>
          <target state="translated">Recupera um provedor de Automação da Interface do Usuário para cada elemento filho selecionado.</target>       </trans-unit>
        <trans-unit id="149" translate="yes" xml:space="preserve" uid="M:System.Windows.Automation.Peers.DataGridItemAutomationPeer.System#Windows#Automation#Provider#ISelectionProvider#GetSelection">
          <source>A collection of UI Automation providers.</source>
          <target state="translated">Uma coleção de provedores de Automação da Interface do Usuário.</target>       </trans-unit>
        <trans-unit id="150" translate="yes" xml:space="preserve" extradata="MT" uid="M:System.Windows.Automation.Peers.DataGridItemAutomationPeer.System#Windows#Automation#Provider#ISelectionProvider#GetSelection">
          <source>This member is an explicit interface member implementation.</source>
          <target state="translated">Este membro é uma implementação do membro de interface explícita.</target>       </trans-unit>
        <trans-unit id="151" translate="yes" xml:space="preserve" extradata="MT" uid="M:System.Windows.Automation.Peers.DataGridItemAutomationPeer.System#Windows#Automation#Provider#ISelectionProvider#GetSelection">
          <source>It can be used only when the <ph id="ph1">&lt;xref:System.Windows.Automation.Peers.DataGridItemAutomationPeer&gt;</ph> instance is cast to an <ph id="ph2">&lt;xref:System.Windows.Automation.Provider.ISelectionProvider&gt;</ph> interface.</source>
          <target state="translated">Ele só pode ser usado quando a instância de <ph id="ph1">&lt;xref:System.Windows.Automation.Peers.DataGridItemAutomationPeer&gt;</ph> é convertida em uma interface de <ph id="ph2">&lt;xref:System.Windows.Automation.Provider.ISelectionProvider&gt;</ph>.</target>       </trans-unit>
        <trans-unit id="152" translate="yes" xml:space="preserve" uid="P:System.Windows.Automation.Peers.DataGridItemAutomationPeer.System#Windows#Automation#Provider#ISelectionProvider#IsSelectionRequired">
          <source>Gets a value that specifies whether the UI Automation provider requires at least one child element to be selected.</source>
          <target state="translated">Obtém um valor que especifica se o provedor de Automação da Interface do Usuário exige que, pelo menos, um elemento filho seja selecionado.</target>       </trans-unit>
        <trans-unit id="153" translate="yes" xml:space="preserve" extradata="MT" uid="P:System.Windows.Automation.Peers.DataGridItemAutomationPeer.System#Windows#Automation#Provider#ISelectionProvider#IsSelectionRequired">
          <source><ph id="ph1">&lt;see langword="false" /&gt;</ph> in all cases.</source>
          <target state="translated"><ph id="ph1">&lt;see langword="false" /&gt;</ph> em todos os casos.</target>       </trans-unit>
        <trans-unit id="154" translate="yes" xml:space="preserve" extradata="MT" uid="P:System.Windows.Automation.Peers.DataGridItemAutomationPeer.System#Windows#Automation#Provider#ISelectionProvider#IsSelectionRequired">
          <source>This member is an explicit interface member implementation.</source>
          <target state="translated">Este membro é uma implementação do membro de interface explícita.</target>       </trans-unit>
        <trans-unit id="155" translate="yes" xml:space="preserve" extradata="MT" uid="P:System.Windows.Automation.Peers.DataGridItemAutomationPeer.System#Windows#Automation#Provider#ISelectionProvider#IsSelectionRequired">
          <source>It can be used only when the <ph id="ph1">&lt;xref:System.Windows.Automation.Peers.DataGridItemAutomationPeer&gt;</ph> instance is cast to an <ph id="ph2">&lt;xref:System.Windows.Automation.Provider.ISelectionProvider&gt;</ph> interface.</source>
          <target state="translated">Ele só pode ser usado quando a instância de <ph id="ph1">&lt;xref:System.Windows.Automation.Peers.DataGridItemAutomationPeer&gt;</ph> é convertida em uma interface de <ph id="ph2">&lt;xref:System.Windows.Automation.Provider.ISelectionProvider&gt;</ph>.</target>       </trans-unit>
      </group>
    </body>
  </file>
</xliff>