<?xml version="1.0" encoding="utf-8"?>
<xliff xmlns="urn:oasis:names:tc:xliff:document:1.2" xmlns:xsi="http://www.w3.org/2001/XMLSchema-instance" version="1.2" xsi:schemaLocation="urn:oasis:names:tc:xliff:document:1.2 xliff-core-1.2-transitional.xsd">
  <file datatype="xml" original="HideModuleNameAttribute.xml" source-language="en-US" target-language="pt-BR">
    <header>
      <tool tool-id="mdxliff" tool-name="mdxliff" tool-version="1.0-15c36f0" tool-company="Microsoft" />
      <xliffext:skl_file_name xmlns:xliffext="urn:microsoft:content:schema:xliffextensions">02cd5861-7ce2-4a82-b358-31f8435a0ac59c0f7c2106f7623defa21c73d88fe203d239fd43.skl</xliffext:skl_file_name>
      <xliffext:version xmlns:xliffext="urn:microsoft:content:schema:xliffextensions">1.2</xliffext:version>
      <xliffext:ms.openlocfilehash xmlns:xliffext="urn:microsoft:content:schema:xliffextensions">9c0f7c2106f7623defa21c73d88fe203d239fd43</xliffext:ms.openlocfilehash>
      <xliffext:ms.sourcegitcommit xmlns:xliffext="urn:microsoft:content:schema:xliffextensions">d31dc2ede16f6f7bc64e90d9f897ff54c4e3869b</xliffext:ms.sourcegitcommit>
      <xliffext:ms.lasthandoff xmlns:xliffext="urn:microsoft:content:schema:xliffextensions">04/03/2018</xliffext:ms.lasthandoff>
      <xliffext:moniker_ids xmlns:xliffext="urn:microsoft:content:schema:xliffextensions">netcore-1.0,netcore-1.1,netcore-2.0,netcore-2.1,netframework-4.5.1,netframework-4.5.2,netframework-4.5,netframework-4.6.1,netframework-4.6.2,netframework-4.6,netframework-4.7.1,netframework-4.7</xliffext:moniker_ids>
    </header>
    <body>
      <group id="content" extype="content">
        <trans-unit id="101" translate="yes" xml:space="preserve" uid="T:Microsoft.VisualBasic.HideModuleNameAttribute">
          <source>The <ph id="ph1">&lt;see langword="HideModuleNameAttribute" /&gt;</ph> attribute, when applied to a module, allows the module members to be accessed using only the qualification needed for the module.</source>
          <target state="translated">O atributo <ph id="ph1">&lt;see langword="HideModuleNameAttribute" /&gt;</ph>, quando aplicado a um módulo, permite que os membros de módulo sejam acessados usando somente a qualificação necessária para o módulo.</target>       </trans-unit>
        <trans-unit id="102" translate="yes" xml:space="preserve" extradata="MT" uid="T:Microsoft.VisualBasic.HideModuleNameAttribute">
          <source>This attribute is useful for exposing module members without showing the module itself.</source>
          <target state="translated">Esse atributo é útil para expor os membros do módulo sem mostrar o próprio módulo.</target>       </trans-unit>
        <trans-unit id="103" translate="yes" xml:space="preserve" extradata="MT" uid="T:Microsoft.VisualBasic.HideModuleNameAttribute">
          <source>When using IntelliSense in the <ph id="ph1">[!INCLUDE[vsprvs](~/includes/vsprvs-md.md)]</ph> Integrated Development Environment (IDE) for <ph id="ph2">[!INCLUDE[vbprvb](~/includes/vbprvb-md.md)]</ph>, the module does not show in the statement completion list.</source>
          <target state="translated">Ao usar o IntelliSense a <ph id="ph1">[!INCLUDE[vsprvs](~/includes/vsprvs-md.md)]</ph> ambiente de desenvolvimento integrado (IDE) para <ph id="ph2">[!INCLUDE[vbprvb](~/includes/vbprvb-md.md)]</ph>, o módulo não aparece na lista de conclusão de instrução.</target>       </trans-unit>
        <trans-unit id="104" translate="yes" xml:space="preserve" extradata="MT" uid="T:Microsoft.VisualBasic.HideModuleNameAttribute">
          <source>Instead, IntelliSense shows the module members.</source>
          <target state="translated">Em vez disso, o IntelliSense exibe os membros do módulo.</target>       </trans-unit>
        <trans-unit id="105" translate="yes" xml:space="preserve" extradata="MT" uid="T:Microsoft.VisualBasic.HideModuleNameAttribute">
          <source>Even when the module name is hidden, the module members are still accessible through the module.</source>
          <target state="translated">Mesmo quando o nome do módulo é ocultado, os membros do módulo ainda são acessíveis por meio do módulo.</target>       </trans-unit>
        <trans-unit id="106" translate="yes" xml:space="preserve" extradata="MT" uid="T:Microsoft.VisualBasic.HideModuleNameAttribute">
          <source>If a member name conflicts with another identifier or with a member of another module with the <ph id="ph1">`HideModuleNameAttribute`</ph> attribute, then the member does not show in IntelliSense at the level of the module.</source>
          <target state="translated">Se um nome de membro está em conflito com outro identificador ou um membro de outro módulo com o <ph id="ph1">`HideModuleNameAttribute`</ph> de atributo, em seguida, o membro não aparece no IntelliSense no nível de módulo.</target>       </trans-unit>
        <trans-unit id="107" translate="yes" xml:space="preserve" extradata="MT" uid="T:Microsoft.VisualBasic.HideModuleNameAttribute">
          <source>This example shows how to use the <ph id="ph1">`HideModuleNameAttribute`</ph> attribute to add a Database object to <ph id="ph2">`My`</ph>, which can be accessed through <ph id="ph3">`My.Database`</ph>.</source>
          <target state="translated">Este exemplo mostra como usar o <ph id="ph1">`HideModuleNameAttribute`</ph> atributo a ser adicionado a um objeto de banco de dados <ph id="ph2">`My`</ph>, que pode ser acessado por meio de <ph id="ph3">`My.Database`</ph>.</target>       </trans-unit>
        <trans-unit id="108" translate="yes" xml:space="preserve" extradata="MT" uid="T:Microsoft.VisualBasic.HideModuleNameAttribute">
          <source>The <ph id="ph1">`Namespace`</ph> statement must appear outside of any classes or modules.</source>
          <target state="translated">O <ph id="ph1">`Namespace`</ph> declaração deve aparecer fora de qualquer classes ou módulos.</target>       </trans-unit>
        <trans-unit id="109" translate="yes" xml:space="preserve" uid="M:Microsoft.VisualBasic.HideModuleNameAttribute.#ctor">
          <source>Initializes a new instance of the <ph id="ph1">&lt;see cref="T:Microsoft.VisualBasic.HideModuleNameAttribute" /&gt;</ph> attribute.</source>
          <target state="translated">Inicializa uma nova instância do atributo <ph id="ph1">&lt;see cref="T:Microsoft.VisualBasic.HideModuleNameAttribute" /&gt;</ph>.</target>       </trans-unit>
      </group>
    </body>
  </file>
</xliff>